Workbook

Sheet Assumptions
A1: DECKERS OUTDOOR (DECK) — MODEL ASSUMPTIONS
B2: FY2023A | C2: FY2024A | D2: FY2025A | E2: FY2026E | F2: FY2027E | G2: FY2028E
A3: REVENUE ASSUMPTIONS
A4: Revenue Growth % (YoY) | C4: 0.1822 | D4: 0.1628 | E4: 0.1 | F4: 0.09 | G4: 0.08
A5: HOKA Revenue ($K) | B5: 1412916 | C5: 1806740 | D5: 2233090
A6: UGG Revenue ($K) | B6: 1929211 | C6: 2239132 | D6: 2531351
A7: Other Brands ($K) | B7: 285159 | C7: 241891 | D7: 221171
A8: MARGIN ASSUMPTIONS
A9: Gross Margin % | B9: 0.503 | C9: 0.5562 | D9: 0.5787 | E9: 0.58 | F9: 0.565 | G9: 0.568
A10: SG&A % of Revenue | B10: 0.3232 | C10: 0.34 | D10: 0.3423 | E10: 0.338 | F10: 0.35 | G10: 0.348
A11: EBIT Margin % | B11: 0.1798 | C11: 0.2162 | D11: 0.2364 | E11: 0.242 | F11: 0.247 | G11: 0.25
A12: Effective Tax Rate % | B12: 0.2241 | C12: 0.2241 | D12: 0.2228 | E12: 0.223 | F12: 0.23 | G12: 0.23
A13: WORKING CAPITAL ASSUMPTIONS (days)
A14: Days Sales Outstanding (DSO) | B14: 30 | C14: 25 | D14: 24 | E14: 25 | F14: 25 | G14: 25
A15: Days Inventory Outstanding (DIO) | B15: 108 | C15: 91 | D15: 86 | E15: 88 | F15: 87 | G15: 86
A16: Days Payable Outstanding (DPO) | B16: 54 | C16: 73 | D16: 73 | E16: 73 | F16: 73 | G16: 73
A17: CAPEX & D&A
A18: Capex % of Revenue | B18: 0.0223 | C18: 0.0208 | D18: 0.0173 | E18: 0.02 | F18: 0.022 | G18: 0.022
A19: D&A % of Revenue | B19: 0.0132 | C19: 0.0134 | D19: 0.0139 | E19: 0.014 | F19: 0.014 | G19: 0.014
A20: DCF ASSUMPTIONS
A21: WACC | E21: 0.1
A22: Terminal Growth Rate | E22: 0.03
A23: Shares Outstanding (K) | E23: 141502
A24: Net Cash ($K) | E24: 1889188
A25: Beta (5-yr monthly) | E25: 1.15
A26: Risk-Free Rate | E26: 0.045
A27: Equity Risk Premium | E27: 0.05
A28: Cost of Debt | E28: 0.055
A30: Yellow cells = change these to run scenarios. Historical ratios computed from exact 10-K filings (FY2023-2025).

Sheet Income Statement
A1: DECKERS OUTDOOR (DECK) — INCOME STATEMENT ($000s, fiscal year ends March 31)
B2: FY2023A | C2: FY2024A | D2: FY2025A | E2: FY2026E | F2: FY2027E | G2: FY2028E
A3: REVENUE
A4: Net Revenue | B4: 3627286 | C4: 4287763 | D4: 4985612 | E4: =D4*(1+Assumptions!E4) -> 5484173.2 | F4: =E4*(1+Assumptions!F4) -> 5977748.8 | G4: =F4*(1+Assumptions!G4) -> 6455968.7
A5: COST & MARGIN
A6: Cost of Sales | B6: 1801916 | C6: 1902275 | D6: 2099949 | E6: =E4-E7 -> 2303352.7 | F6: =F4-F7 -> 2600320.7 | G6: =G4-G7 -> 2788978.5
A7: Gross Profit | B7: 1825370 | C7: 2385488 | D7: 2885663 | E7: =E4*Assumptions!E9 -> 3180820.5 | F7: =F4*Assumptions!F9 -> 3377428.1 | G7: =G4*Assumptions!G9 -> 3666990.2
A8: Gross Margin % | B8: 0.503 | C8: 0.5562 | D8: 0.5787 | E8: =E7/E4 -> 0.58 | F8: =F7/F4 -> 0.565 | G8: =G7/G4 -> 0.568
A9: OPERATING EXPENSES
A10: SG&A Expenses | B10: 1172619 | C10: 1457974 | D10: 1706571 | E10: =E4*Assumptions!E10 -> 1853650.5 | F10: =F4*Assumptions!F10 -> 2092212.1 | G10: =G4*Assumptions!G10 -> 2246677.1
A11: SG&A % of Revenue | B11: 0.3232 | C11: 0.34 | D11: 0.3423 | E11: =E10/E4 -> 0.338 | F11: =F10/F4 -> 0.35 | G11: =G10/G4 -> 0.348
A12: EBIT (Operating Income) | B12: 652751 | C12: 927514 | D12: 1179092 | E12: =E7-E10 -> 1327169.9 | F12: =F7-F10 -> 1285216 | G12: =G7-G10 -> 1420313.1
A13: EBIT Margin % | B13: 0.1798 | C13: 0.2162 | D13: 0.2364 | E13: =E12/E4 -> 0.242 | F13: =F12/F4 -> 0.215 | G13: =G12/G4 -> 0.22
A14: BELOW THE LINE
A15: Interest Income | B15: 15563 | C15: 52208 | D15: 68389 | E15: =D15 -> 68389 | F15: =E15 -> 68389 | G15: =F15 -> 68389
A16: Interest Expense | B16: -3442 | C16: -2564 | D16: -3517 | E16: =D16 -> -3517 | F16: =E16 -> -3517 | G16: =F16 -> -3517
A17: Pre-Tax Income | B17: 666082 | C17: 978941 | D17: 1243299 | E17: =E12+E15+E16 -> 1392041.9 | F17: =F12+F15+F16 -> 1350088 | G17: =G12+G15+G16 -> 1485185.1
A18: Income Tax Expense | B18: 149260 | C18: 219378 | D18: 277208 | E18: =E17*Assumptions!E12 -> 310425.35 | F18: =F17*Assumptions!F12 -> 310520.24 | G18: =G17*Assumptions!G12 -> 341592.58
A19: Effective Tax Rate % | B19: 0.2241 | C19: 0.2241 | D19: 0.2228 | E19: =E18/E17 -> 0.223 | F19: =F18/F17 -> 0.23 | G19: =G18/G17 -> 0.23
A20: Net Income | B20: 516822 | C20: 759563 | D20: 966091 | E20: =E17-E18 -> 1081616.6 | F20: =F17-F18 -> 1039567.8 | G20: =G17-G18 -> 1143592.5
A21: Net Margin % | B21: 0.1425 | C21: 0.1971 | D21: 0.1938 | E21: =E20/E4 -> 0.19722509 | F21: =F20/F4 -> 0.17390623 | G21: =G20/G4 -> 0.17713725
A22: EBITDA BRIDGE
A23: D&A (from CF statement) | B23: 47858 | C23: 57587 | D23: 69353 | E23: =E4*Assumptions!E19 -> 76778.425 | F23: =F4*Assumptions!F19 -> 83688.483 | G23: =G4*Assumptions!G19 -> 90383.562
A24: EBITDA | B24: 700609 | C24: 985101 | D24: 1248445 | E24: =E12+E23 -> 1403948.3 | F24: =F12+F23 -> 1368904.5 | G24: =G12+G23 -> 1510696.7
A25: EBITDA Margin % | B25: 0.1931 | C25: 0.2297 | D25: 0.2504 | E25: =E24/E4 -> 0.256 | F25: =F24/F4 -> 0.229 | G25: =G24/G4 -> 0.234
A27: Historical figures from Deckers 10-K filings (FY2023: March 2023, FY2024: March 2024, FY2025: March 2025). D&A from cash flow statement (non-cash add-back line).

Sheet Balance Sheet
A1: DECKERS OUTDOOR (DECK) — BALANCE SHEET ($000s, as of March 31)
B2: FY2023A | C2: FY2024A | D2: FY2025A | E2: FY2026E | F2: FY2027E | G2: FY2028E
A3: ASSETS
A4: Current Assets
A5: Cash & Equivalents | B5: 981795 | C5: 1502051 | D5: 1889188 | E5: ='Cash Flow'!E29 -> 1840698.9 | F5: ='Cash Flow'!F29 -> 2038859.3 | G5: ='Cash Flow'!G29 -> 2258366.9
A6: Trade Accounts Receivable, net | B6: 301511 | C6: 296565 | D6: 332872 | E6: =Assumptions!E14/365*'Income Statement'!E4 -> 375628.3 | F6: =Assumptions!F14/365*'Income Statement'!F4 -> 409434.85 | G6: =Assumptions!G14/365*'Income Statement'!G4 -> 442189.64
A7: Inventories | B7: 532852 | C7: 474311 | D7: 495226 | E7: =Assumptions!E15/365*'Income Statement'!E6 -> 555328.88 | F7: =Assumptions!F15/365*'Income Statement'!F6 -> 619802.47 | G7: =Assumptions!G15/365*'Income Statement'!G6 -> 657129.17
A8: Prepaid Expenses | B8: 33788 | C8: 34284 | D8: 39294 | E8: =D8 -> 39294 | F8: =E8 -> 39294 | G8: =F8 -> 39294
A9: Other Current Assets | B9: 55523 | C9: 92713 | D9: 67282 | E9: =D9 -> 67282 | F9: =E9 -> 67282 | G9: =F9 -> 67282
A10: Income Tax Receivable | B10: 4784 | C10: 43559 | D10: 36613 | E10: =D10 -> 36613 | F10: =E10 -> 36613 | G10: =F10 -> 36613
A11: Total Current Assets | B11: 1910253 | C11: 2443483 | D11: 2860475 | E11: =SUM(E5:E10) -> 2914845.1 | F11: =SUM(F5:F10) -> 3211285.7 | G11: =SUM(G5:G10) -> 3500874.7
A12: Property & Equipment, net | B12: 266679 | C12: 302122 | D12: 325599 | E12: =D12+'Cash Flow'!E17*-1-'Income Statement'!E23 -> 358504.04 | F12: =E12+'Cash Flow'!F17*-1-'Income Statement'!F23 -> 406326.03 | G12: =F12+'Cash Flow'!G17*-1-'Income Statement'!G23 -> 457973.78
A13: Operating Lease Assets | B13: 213302 | C13: 225669 | D13: 237352 | E13: =D13 -> 237352 | F13: =E13 -> 237352 | G13: =F13 -> 237352
A14: Goodwill | B14: 13990 | C14: 13990 | D14: 13990 | E14: =D14 -> 13990 | F14: =E14 -> 13990 | G14: =F14 -> 13990
A15: Other Intangible Assets, net | B15: 37457 | C15: 27083 | D15: 15699 | E15: =D15 -> 15699 | F15: =E15 -> 15699 | G15: =F15 -> 15699
A16: Deferred Tax Assets, net | B16: 72592 | C16: 72584 | D16: 77591 | E16: =D16 -> 77591 | F16: =E16 -> 77591 | G16: =F16 -> 77591
A17: Other Assets | B17: 41930 | C17: 50648 | D17: 39546 | E17: =D17 -> 39546 | F17: =E17 -> 39546 | G17: =F17 -> 39546
A18: Total Assets | B18: 2556203 | C18: 3135579 | D18: 3570252 | E18: =E11+SUM(E12:E17) -> 3657527.1 | F18: =F11+SUM(F12:F17) -> 4001789.7 | G18: =G11+SUM(G12:G17) -> 4343026.5
A20: LIABILITIES & STOCKHOLDERS EQUITY
A21: Current Liabilities
A22: Trade Accounts Payable | B22: 265605 | C22: 378503 | D22: 417955 | E22: =Assumptions!E16/365*'Income Statement'!E6 -> 460670.55 | F22: =Assumptions!F16/365*'Income Statement'!F6 -> 520064.14 | G22: =Assumptions!G16/365*'Income Statement'!G6 -> 557795.69
A23: Accrued Payroll | B23: 63781 | C23: 123653 | D23: 125417 | E23: =D23 -> 125417 | F23: =E23 -> 125417 | G23: =F23 -> 125417
A24: Operating Lease Liabilities | B24: 50765 | C24: 53581 | D24: 54453 | E24: =D24 -> 54453 | F24: =E24 -> 54453 | G24: =F24 -> 54453
A25: Other Accrued Expenses | B25: 86753 | C25: 106785 | D25: 142120 | E25: =D25 -> 142120 | F25: =E25 -> 142120 | G25: =F25 -> 142120
A26: Income Tax Payable | B26: 17322 | C26: 52338 | D26: 23299 | E26: =D26 -> 23299 | F26: =E26 -> 23299 | G26: =F26 -> 23299
A27: Value Added Tax Payable | B27: 13154 | C27: 5133 | D27: 6697 | E27: =D27 -> 6697 | F27: =E27 -> 6697 | G27: =F27 -> 6697
A28: Total Current Liabilities | B28: 497380 | C28: 719993 | D28: 769941 | E28: =SUM(E22:E27) -> 812656.55 | F28: =SUM(F22:F27) -> 872050.14 | G28: =SUM(G22:G27) -> 909781.69
A29: Long-Term Operating Lease Liab. | B29: 195723 | C29: 213298 | D29: 222522 | E29: =D29 -> 222522 | F29: =E29 -> 222522 | G29: =F29 -> 222522
A30: Income Tax Liability (LT) | B30: 62032 | C30: 52470 | D30: 13587 | E30: =D30 -> 13587 | F30: =E30 -> 13587 | G30: =F30 -> 13587
A31: Other Long-Term Liabilities | B31: 35335 | C31: 42350 | D31: 51189 | E31: =D31 -> 51189 | F31: =E31 -> 51189 | G31: =F31 -> 51189
A32: Total Long-Term Liabilities | B32: 293090 | C32: 308118 | D32: 287298 | E32: =SUM(E29:E31) -> 287298 | F32: =SUM(F29:F31) -> 287298 | G32: =SUM(G29:G31) -> 287298
A33: Total Liabilities | B33: 790470 | C33: 1028111 | D33: 1057239 | E33: =E28+E32 -> 1099954.5 | F33: =F28+F32 -> 1159348.1 | G33: =G28+G32 -> 1197079.7
A35: Common Stock | B35: 262 | C35: 1536 | D35: 1502 | E35: =D35 -> 1502 | F35: =E35 -> 1502 | G35: =F35 -> 1502
A36: Additional Paid-In Capital | B36: 232932 | C36: 243050 | D36: 253466 | E36: =D36+'Cash Flow'!E6 -> 291409 | F36: =E36+'Cash Flow'!F6 -> 329352 | G36: =F36+'Cash Flow'!G6 -> 367295
A37: Retained Earnings | B37: 1571574 | C37: 1913615 | D37: 2307699 | E37: =D37+'Income Statement'!E20+'Cash Flow'!E21 -> 2314315.6 | F37: =E37+'Income Statement'!F20+'Cash Flow'!F21 -> 2561241.5 | G37: =F37+'Income Statement'!G20+'Cash Flow'!G21 -> 2826803.8
A38: AOCI | B38: -39035 | C38: -50733 | D38: -49654 | E38: =D38 -> -49654 | F38: =E38 -> -49654 | G38: =F38 -> -49654
A39: Total Stockholders Equity | B39: 1765733 | C39: 2107468 | D39: 2513013 | E39: =SUM(E35:E38) -> 2557572.6 | F39: =SUM(F35:F38) -> 2842441.5 | G39: =SUM(G35:G38) -> 3145946.8
A40: Total Liabilities & Equity | B40: 2556203 | C40: 3135579 | D40: 3570252 | E40: =E33+E39 -> 3657527.1 | F40: =F33+F39 -> 4001789.7 | G40: =G33+G39 -> 4343026.5
A42: CHECK: BS Balances (must = 0) | B42: =B18-B40 -> 0 | C42: =C18-C40 -> 0 | D42: =D18-D40 -> 0 | E42: =E18-E40 -> 0 | F42: =F18-F40 -> 0 | G42: =G18-G40 -> 0
A44: FY2023 from FY2024 10-K comparative column. FY2024 and FY2025 from respective 10-K filings. CHECK row must equal 0.

Sheet Cash Flow
A1: DECKERS OUTDOOR (DECK) — CASH FLOW STATEMENT ($000s)
B2: FY2023A | C2: FY2024A | D2: FY2025A | E2: FY2026E | F2: FY2027E | G2: FY2028E
A3: OPERATING ACTIVITIES
A4: Net Income | B4: 516822 | C4: 759563 | D4: 966091 | E4: ='Income Statement'!E20 -> 1081616.6 | F4: ='Income Statement'!F20 -> 1039567.8 | G4: ='Income Statement'!G20 -> 1143592.5
A5: + Depreciation & Amortization | B5: 47858 | C5: 57587 | D5: 69353 | E5: ='Income Statement'!E23 -> 76778.425 | F5: ='Income Statement'!F23 -> 83688.483 | G5: ='Income Statement'!G23 -> 90383.562
A6: + Stock-Based Compensation | B6: 26897 | C6: 37288 | D6: 37943 | E6: ='Cash Flow'!D6 -> 37943 | F6: ='Cash Flow'!D6 -> 37943 | G6: ='Cash Flow'!D6 -> 37943
A7: + Other Non-Cash Items | B7: 3953 | C7: 6826 | D7: 9700 | E7: =0 -> 0 | F7: =0 -> 0 | G7: =0 -> 0
A8: - Change in Trade Receivables | B8: -5609 | C8: -38490 | D8: -41339 | E8: =-('Balance Sheet'!E6-'Balance Sheet'!D6) -> -42756.301 | F8: =-('Balance Sheet'!F6-'Balance Sheet'!E6) -> -33806.547 | G8: =-('Balance Sheet'!G6-'Balance Sheet'!F6) -> -32754.788
A9: - Change in Inventories | B9: -26056 | C9: 58541 | D9: -24344 | E9: =-('Balance Sheet'!E7-'Balance Sheet'!D7) -> -60102.881 | F9: =-('Balance Sheet'!F7-'Balance Sheet'!E7) -> -64473.593 | G9: =-('Balance Sheet'!G7-'Balance Sheet'!F7) -> -37326.701
A10: +/- Change in Prepaid & Other | B10: 13459 | C10: 4157 | D10: 20946 | E10: =0 -> 0 | F10: =0 -> 0 | G10: =0 -> 0
A11: + Change in Trade Payables | B11: -74247 | C11: 119601 | D11: 35636 | E11: =('Balance Sheet'!E22-'Balance Sheet'!D22) -> 42715.549 | F11: =('Balance Sheet'!F22-'Balance Sheet'!E22) -> 59393.596 | G11: =('Balance Sheet'!G22-'Balance Sheet'!F22) -> 37731.55
A12: +/- Change in Other Accrued | B12: 11528 | C12: 43534 | D12: 22222 | E12: =0 -> 0 | F12: =0 -> 0 | G12: =0 -> 0
A13: +/- Change in Tax Payable | B13: 4897 | C13: 35016 | D13: -29039 | E13: =0 -> 0 | F13: =0 -> 0 | G13: =0 -> 0
A14: +/- Other Operating | B14: 17920 | C14: -50439 | D14: -22646 | E14: =0 -> 0 | F14: =0 -> 0 | G14: =0 -> 0
A15: Cash from Operations | B15: 537422 | C15: 1033184 | D15: 1044523 | E15: =SUM(E4:E14) -> 1136194.4 | F15: =SUM(F4:F14) -> 1122312.7 | G15: =SUM(G4:G14) -> 1239569.2
A16: INVESTING ACTIVITIES
A17: Capital Expenditures | B17: -81025 | C17: -89365 | D17: -86171 | E17: =-'Income Statement'!E4*Assumptions!E18 -> -109683.46 | F17: =-'Income Statement'!F4*Assumptions!F18 -> -131510.47 | G17: =-'Income Statement'!G4*Assumptions!G18 -> -142031.31
A18: Proceeds from Asset Sales | B18: 12 | C18: 34 | D18: 11168 | E18: =0 -> 0 | F18: =0 -> 0 | G18: =0 -> 0
A19: Cash from Investing | B19: -81013 | C19: -89331 | D19: -75003 | E19: =E17+E18 -> -109683.46 | F19: =F17+F18 -> -131510.47 | G19: =G17+G18 -> -142031.31
A20: FINANCING ACTIVITIES
A21: Share Repurchases | B21: -297372 | C21: -414931 | D21: -567002 | E21: -1075000 | F21: =-0.8*F31 -> -792641.77 | G21: =-0.8*G31 -> -878030.28
A22: Stock Issuance & Options | B22: 6566 | C22: 7230 | D22: 4772 | E22: =0 -> 0 | F22: =0 -> 0 | G22: =0 -> 0
A23: Other Financing | B23: -18225 | C23: -9974 | D23: -3985 | E23: =0 -> 0 | F23: =0 -> 0 | G23: =0 -> 0
A24: Cash from Financing | B24: -309031 | C24: -417675 | D24: -581334 | E24: =E21+E22+E23 -> -1075000 | F24: =F21+F22+F23 -> -792641.77 | G24: =G21+G22+G23 -> -878030.28
A25: FX Effect on Cash | B25: -9110 | C25: -5922 | D25: -1049 | E25: =0 -> 0 | F25: =0 -> 0 | G25: =0 -> 0
A26: NET CHANGE & RECONCILIATION
A27: Net Change in Cash | B27: 138268 | C27: 520256 | D27: 387137 | E27: =E15+E19+E24+E25 -> -48489.105 | F27: =F15+F19+F24+F25 -> 198160.44 | G27: =G15+G19+G24+G25 -> 219507.57
A28: Beginning Cash | B28: 843527 | C28: 981795 | D28: 1502051 | E28: =D29 -> 1889188 | F28: =E29 -> 1840698.9 | G28: =F29 -> 2038859.3
A29: Ending Cash | B29: 981795 | C29: 1502051 | D29: 1889188 | E29: =E28+E27 -> 1840698.9 | F29: =F28+F27 -> 2038859.3 | G29: =G28+G27 -> 2258366.9
A30: FREE CASH FLOW
A31: FCF (Cash from Ops - Capex) | B31: 456397 | C31: 943819 | D31: 958352 | E31: =E15+E17 -> 1026510.9 | F31: =F15+F17 -> 990802.22 | G31: =G15+G17 -> 1097537.8
A32: FCF Margin % | B32: 0.1258 | C32: 0.2201 | D32: 0.1922 | E32: =E31/'Income Statement'!E4 -> 0.18717696 | F32: =F31/'Income Statement'!F4 -> 0.16574839 | G32: =G31/'Income Statement'!G4 -> 0.17000359
A33: FCF Conversion (FCF / NI) | B33: 0.883 | C33: 1.243 | D33: 0.992 | E33: =E31/'Income Statement'!E20 -> 0.94905249 | F33: =F31/'Income Statement'!F20 -> 0.95309057 | G33: =G31/'Income Statement'!G20 -> 0.95972806
A35: FY2025 from DECK FY2025 annual report p.F-8. FY2024 and FY2023 from FY2024 10-K p.F-8. FCF = CFO - Capex.

Sheet DCF
A1: DECKERS OUTDOOR (DECK) — DCF VALUATION
B2: FY2026E | C2: FY2027E | D2: FY2028E
A3: STEP 1 — UNLEVERED FREE CASH FLOW
A4: Revenue | B4: ='Income Statement'!E4 -> 5484173.2 | C4: ='Income Statement'!F4 -> 5977748.8 | D4: ='Income Statement'!G4 -> 6455968.7
A5: EBIT | B5: ='Income Statement'!E12 -> 1327169.9 | C5: ='Income Statement'!F12 -> 1285216 | D5: ='Income Statement'!G12 -> 1420313.1
A6: Tax Rate % | B6: =Assumptions!E12 -> 0.223 | C6: =Assumptions!F12 -> 0.23 | D6: =Assumptions!G12 -> 0.23
A7: NOPAT = EBIT × (1 − t) | B7: =B5*(1-B6) -> 1031211 | C7: =C5*(1-C6) -> 989616.31 | D7: =D5*(1-D6) -> 1093641.1
A8: + D&A | B8: ='Income Statement'!E23 -> 76778.425 | C8: ='Income Statement'!F23 -> 83688.483 | D8: ='Income Statement'!G23 -> 90383.562
A9: − Capex | B9: ='Cash Flow'!E17 -> -109683.46 | C9: ='Cash Flow'!F17 -> -131510.47 | D9: ='Cash Flow'!G17 -> -142031.31
A10: − Δ Net Working Capital | B10: =-(('Balance Sheet'!E6+'Balance Sheet'!E7-'Balance Sheet'!E22)-('Balance Sheet'!D6+'Balance Sheet'!D7-'Balance Sheet'!D22)) -> -60143.633 | C10: =-(('Balance Sheet'!F6+'Balance Sheet'!F7-'Balance Sheet'!F22)-('Balance Sheet'!E6+'Balance Sheet'!E7-'Balance Sheet'!E22)) -> -38886.544 | D10: =-(('Balance Sheet'!G6+'Balance Sheet'!G7-'Balance Sheet'!G22)-('Balance Sheet'!F6+'Balance Sheet'!F7-'Balance Sheet'!F22)) -> -32349.939
A11: Unlevered FCF | B11: =B7+B8+B9+B10 -> 938162.35 | C11: =C7+C8+C9+C10 -> 902907.78 | D11: =D7+D8+D9+D10 -> 1009643.4
A12: Discount Period | B12: =1 -> 1 | C12: =2 -> 2 | D12: =3 -> 3
A13: Discount Factor (÷WACC=10%) | B13: =1/(1+Assumptions!$E$21)^B12 -> 0.90909091 | C13: =1/(1+Assumptions!$E$21)^C12 -> 0.82644628 | D13: =1/(1+Assumptions!$E$21)^D12 -> 0.7513148
A14: PV of Unlevered FCF | B14: =B11*B13 -> 852874.86 | C14: =C11*C13 -> 746204.77 | D14: =D11*D13 -> 758560.04
A15: STEP 2 — TERMINAL VALUE & ENTERPRISE VALUE
A16: Sum of PV of FCFs ($K) | B16: =SUM(B14:D14) -> 2357639.7
A17: Terminal Year FCF ($K) | B17: =D11 -> 1009643.4
A18: Terminal Value = TV FCF×(1+g)/(WACC−g) | B18: =B17*(1+Assumptions!E22)/(Assumptions!E21-Assumptions!E22) -> 14856182
A19: PV of Terminal Value ($K) | B19: =B18*D13 -> 11161669
A20: Enterprise Value ($K) | B20: =B16+B19 -> 13519309
A22: STEP 3 — BRIDGE TO EQUITY VALUE
A23: Enterprise Value ($K) | B23: =B20 -> 13519309
A24: + Cash & Equivalents ($K) | B24: ='Balance Sheet'!D5 -> 1889188
A25: − Total Debt ($K) | B25: =0 -> 0
A26: − Other Long-Term Liabilities ($K) | B26: =0 -> 0
A27: Equity Value ($K) | B27: =B23+B24-B25-B26 -> 15408497
A28: Shares Outstanding (K) | B28: =Assumptions!E23 -> 141502
A29: Implied Share Price | B29: =B27/B28 -> 108.89243
A30: Current Share Price (verify live) | B30: 109
A31: Upside / (Downside) % | B31: =B29/B30-1 -> -0.00098687115
A32: STEP 4 — SENSITIVITY: IMPLIED SHARE PRICE vs WACC & TERMINAL GROWTH
A33: Terminal Growth Rate → | C33: 0.02 | D33: 0.025 | E33: 0.03 | F33: 0.035 | G33: 0.04
A34: WACC ↓ | B34: 0.09 | C34: =(($B$11/(1+$B$34)^1+$C$11/(1+$B$34)^2+$D$11/(1+$B$34)^3)+($D$11*(1+C$33)/($B$34-C$33))/(1+$B$34)^3+$B$24)/$B$28 -> 110.59772 | D34: =(($B$11/(1+$B$34)^1+$C$11/(1+$B$34)^2+$D$11/(1+$B$34)^3)+($D$11*(1+D$33)/($B$34-D$33))/(1+$B$34)^3+$B$24)/$B$28 -> 117.19722 | E34: =(($B$11/(1+$B$34)^1+$C$11/(1+$B$34)^2+$D$11/(1+$B$34)^3)+($D$11*(1+E$33)/($B$34-E$33))/(1+$B$34)^3+$B$24)/$B$28 -> 124.89664 | F34: =(($B$11/(1+$B$34)^1+$C$11/(1+$B$34)^2+$D$11/(1+$B$34)^3)+($D$11*(1+F$33)/($B$34-F$33))/(1+$B$34)^3+$B$24)/$B$28 -> 133.99595 | G34: =(($B$11/(1+$B$34)^1+$C$11/(1+$B$34)^2+$D$11/(1+$B$34)^3)+($D$11*(1+G$33)/($B$34-G$33))/(1+$B$34)^3+$B$24)/$B$28 -> 144.91512
B35: 0.095 | C35: =(($B$11/(1+$B$35)^1+$C$11/(1+$B$35)^2+$D$11/(1+$B$35)^3)+($D$11*(1+C$33)/($B$35-C$33))/(1+$B$35)^3+$B$24)/$B$28 -> 104.07185 | D35: =(($B$11/(1+$B$35)^1+$C$11/(1+$B$35)^2+$D$11/(1+$B$35)^3)+($D$11*(1+D$33)/($B$35-D$33))/(1+$B$35)^3+$B$24)/$B$28 -> 109.7393 | E35: =(($B$11/(1+$B$35)^1+$C$11/(1+$B$35)^2+$D$11/(1+$B$35)^3)+($D$11*(1+E$33)/($B$35-E$33))/(1+$B$35)^3+$B$24)/$B$28 -> 116.27867 | F35: =(($B$11/(1+$B$35)^1+$C$11/(1+$B$35)^2+$D$11/(1+$B$35)^3)+($D$11*(1+F$33)/($B$35-F$33))/(1+$B$35)^3+$B$24)/$B$28 -> 123.90793 | G35: =(($B$11/(1+$B$35)^1+$C$11/(1+$B$35)^2+$D$11/(1+$B$35)^3)+($D$11*(1+G$33)/($B$35-G$33))/(1+$B$35)^3+$B$24)/$B$28 -> 132.92433
B36: 0.1 | C36: =(($B$11/(1+$B$36)^1+$C$11/(1+$B$36)^2+$D$11/(1+$B$36)^3)+($D$11*(1+C$33)/($B$36-C$33))/(1+$B$36)^3+$B$24)/$B$28 -> 98.362342 | D36: =(($B$11/(1+$B$36)^1+$C$11/(1+$B$36)^2+$D$11/(1+$B$36)^3)+($D$11*(1+D$33)/($B$36-D$33))/(1+$B$36)^3+$B$24)/$B$28 -> 103.27638 | E36: =(($B$11/(1+$B$36)^1+$C$11/(1+$B$36)^2+$D$11/(1+$B$36)^3)+($D$11*(1+E$33)/($B$36-E$33))/(1+$B$36)^3+$B$24)/$B$28 -> 108.89243 | F36: =(($B$11/(1+$B$36)^1+$C$11/(1+$B$36)^2+$D$11/(1+$B$36)^3)+($D$11*(1+F$33)/($B$36-F$33))/(1+$B$36)^3+$B$24)/$B$28 -> 115.37249 | G36: =(($B$11/(1+$B$36)^1+$C$11/(1+$B$36)^2+$D$11/(1+$B$36)^3)+($D$11*(1+G$33)/($B$36-G$33))/(1+$B$36)^3+$B$24)/$B$28 -> 122.93255
B37: 0.105 | C37: =(($B$11/(1+$B$37)^1+$C$11/(1+$B$37)^2+$D$11/(1+$B$37)^3)+($D$11*(1+C$33)/($B$37-C$33))/(1+$B$37)^3+$B$24)/$B$28 -> 93.32513 | D37: =(($B$11/(1+$B$37)^1+$C$11/(1+$B$37)^2+$D$11/(1+$B$37)^3)+($D$11*(1+D$33)/($B$37-D$33))/(1+$B$37)^3+$B$24)/$B$28 -> 97.621898 | E37: =(($B$11/(1+$B$37)^1+$C$11/(1+$B$37)^2+$D$11/(1+$B$37)^3)+($D$11*(1+E$33)/($B$37-E$33))/(1+$B$37)^3+$B$24)/$B$28 -> 102.49157 | F37: =(($B$11/(1+$B$37)^1+$C$11/(1+$B$37)^2+$D$11/(1+$B$37)^3)+($D$11*(1+F$33)/($B$37-F$33))/(1+$B$37)^3+$B$24)/$B$28 -> 108.05691 | G37: =(($B$11/(1+$B$37)^1+$C$11/(1+$B$37)^2+$D$11/(1+$B$37)^3)+($D$11*(1+G$33)/($B$37-G$33))/(1+$B$37)^3+$B$24)/$B$28 -> 114.47845
B38: 0.11 | C38: =(($B$11/(1+$B$38)^1+$C$11/(1+$B$38)^2+$D$11/(1+$B$38)^3)+($D$11*(1+C$33)/($B$38-C$33))/(1+$B$38)^3+$B$24)/$B$28 -> 88.848151 | D38: =(($B$11/(1+$B$38)^1+$C$11/(1+$B$38)^2+$D$11/(1+$B$38)^3)+($D$11*(1+D$33)/($B$38-D$33))/(1+$B$38)^3+$B$24)/$B$28 -> 92.63317 | E38: =(($B$11/(1+$B$38)^1+$C$11/(1+$B$38)^2+$D$11/(1+$B$38)^3)+($D$11*(1+E$33)/($B$38-E$33))/(1+$B$38)^3+$B$24)/$B$28 -> 96.891316 | F38: =(($B$11/(1+$B$38)^1+$C$11/(1+$B$38)^2+$D$11/(1+$B$38)^3)+($D$11*(1+F$33)/($B$38-F$33))/(1+$B$38)^3+$B$24)/$B$28 -> 101.71722 | G38: =(($B$11/(1+$B$38)^1+$C$11/(1+$B$38)^2+$D$11/(1+$B$38)^3)+($D$11*(1+G$33)/($B$38-G$33))/(1+$B$38)^3+$B$24)/$B$28 -> 107.23253
B39: 0.115 | C39: =(($B$11/(1+$B$39)^1+$C$11/(1+$B$39)^2+$D$11/(1+$B$39)^3)+($D$11*(1+C$33)/($B$39-C$33))/(1+$B$39)^3+$B$24)/$B$28 -> 84.842938 | D39: =(($B$11/(1+$B$39)^1+$C$11/(1+$B$39)^2+$D$11/(1+$B$39)^3)+($D$11*(1+D$33)/($B$39-D$33))/(1+$B$39)^3+$B$24)/$B$28 -> 88.199229 | E39: =(($B$11/(1+$B$39)^1+$C$11/(1+$B$39)^2+$D$11/(1+$B$39)^3)+($D$11*(1+E$33)/($B$39-E$33))/(1+$B$39)^3+$B$24)/$B$28 -> 91.950378 | F39: =(($B$11/(1+$B$39)^1+$C$11/(1+$B$39)^2+$D$11/(1+$B$39)^3)+($D$11*(1+F$33)/($B$39-F$33))/(1+$B$39)^3+$B$24)/$B$28 -> 96.17042 | G39: =(($B$11/(1+$B$39)^1+$C$11/(1+$B$39)^2+$D$11/(1+$B$39)^3)+($D$11*(1+G$33)/($B$39-G$33))/(1+$B$39)^3+$B$24)/$B$28 -> 100.95313
A42: WACC: CAPM = Rf(4.5%) + β(1.15) × ERP(5.0%) = 10.25%, rounded to 10.0%. No LT debt so WACC ≈ cost of equity. Net cash = $1,889M cash − $0 debt = $1,889M net cash position (debt-free as of FY2025). TV = FCF×(1+g)/(WACC−g). Sensitivity shows how sensitive implied price is to key assumptions.
